examples/__init__.py
examples/train_resnet.py
lightzoo/__init__.py
lightzoo/datasets/__init__.py
lightzoo/datasets/dataloader.py
lightzoo/models/__init__.py
lightzoo/models/base.py
lightzoo/models/resnet.py
lightzoo/models/transformer.py
lightzoo/models/unet.py
lightzoo/models/modules/__init__.py
lightzoo/models/modules/attention.py
lightzoo/models/modules/convolutions.py
lightzoo/utils/__init__.py
lightzoo/utils/load_pretrained.py
tests/__init__.py
tests/test_models.py
tests/test_utils.py
lightzoo-0.1.0.dist-info/METADATA
lightzoo-0.1.0.dist-info/WHEEL
lightzoo-0.1.0.dist-info/top_level.txt
lightzoo-0.1.0.dist-info/RECORD
