Metadata-Version: 2.4
Name: lightzoo
Version: 0.1.0
Summary: A lightweight model zoo for quick prototyping and experimentation.
Home-page: https://github.com/harichselvamc/lightzoo
Author: Harich Selva M C
Author-email: harichselvamc@gmail.com
Classifier: Programming Language :: Python :: 3
Classifier: License :: OSI Approved :: MIT License
Classifier: Operating System :: OS Independent
Requires-Python: >=3.7
Requires-Dist: torch>=1.10
Requires-Dist: torchvision>=0.11
Requires-Dist: transformers>=4.0.0
Dynamic: author
Dynamic: author-email
Dynamic: classifier
Dynamic: home-page
Dynamic: requires-dist
Dynamic: requires-python
Dynamic: summary
